jdvc/__init__.py
jdvc/main.py
jdvc-1.0.1.dist-info/METADATA
jdvc-1.0.1.dist-info/WHEEL
jdvc-1.0.1.dist-info/entry_points.txt
jdvc-1.0.1.dist-info/top_level.txt
jdvc-1.0.1.dist-info/RECORD
